README.md
setup.py
flexet/__init__.py
flexet/cli.py
flexet/configuration.py
flexet/exception.py
flexet/node.py
flexet/parser.py
flexet.egg-info/PKG-INFO
flexet.egg-info/SOURCES.txt
flexet.egg-info/dependency_links.txt
flexet.egg-info/entry_points.txt
flexet.egg-info/requires.txt
flexet.egg-info/top_level.txt
flexet/collector/__init__.py
flexet/collector/pf.py
flexet/collector/plugin.py
tests/__init__.py
tests/run.py
tests/test_initial.py